setup.py
pytooled/__init__.py
pytooled.egg-info/PKG-INFO
pytooled.egg-info/SOURCES.txt
pytooled.egg-info/dependency_links.txt
pytooled.egg-info/top_level.txt
pytooled/_utils/__init__.py
pytooled/_utils/constants.py
pytooled/_utils/tools.py
pytooled/_utils/unions.py
pytooled/color/__init__.py
pytooled/color/base.py
pytooled/color/color.py
pytooled/color/colors/__init__.py
pytooled/color/colors/ansi.py
pytooled/color/colors/cmyk.py
pytooled/color/colors/hex.py
pytooled/color/colors/hexdec.py
pytooled/color/colors/hsb.py
pytooled/color/colors/hsl.py
pytooled/color/colors/hsv.py
pytooled/color/colors/hwb.py
pytooled/color/colors/name.py
pytooled/color/colors/rgb.py
pytooled/tools/__init__.py
pytooled/tools/tools.py
pytooled/typealias/__init__.py
pytooled/typealias/typealias.py