Metadata-Version: 2.1
Name: pytooled
Version: 0.0.1
Summary: Basic tools for python
Author: azzammuhyala
Author-email: azzammuhyala@gmail.com
Keywords: tools,tooled,pytooled,color
